MANIFEST.in
README.txt
setup.py
noody/__init__.py
noody/app.py
noody/session.py
noody_utils.egg-info/PKG-INFO
noody_utils.egg-info/SOURCES.txt
noody_utils.egg-info/dependency_links.txt
noody_utils.egg-info/entry_points.txt
noody_utils.egg-info/namespace_packages.txt
noody_utils.egg-info/top_level.txt